light_health/__init__.py
light_health/registry.py
light_health/status.py
light_health/asgi/__init__.py
light_health/asgi/base.py
light_health/asgi/health.py
light_health/asgi/management.py
light_health/asgi/management_models.py
light_health/checks/__init__.py
light_health/checks/http.py
light_health/checks/mongo.py
light_health/checks/redis.py
light_health-1.0.1.dist-info/licenses/LICENSE
light_health-1.0.1.dist-info/METADATA
light_health-1.0.1.dist-info/WHEEL
light_health-1.0.1.dist-info/top_level.txt
light_health-1.0.1.dist-info/RECORD
