Metadata-Version: 2.4
Name: light-health
Version: 1.0.1
Summary: Lightweight ASGI health checks inspired by Spring Actuator
Author-email: Tiago Ventura <tiago.barbano@gmail.com>
License-Expression: MIT
Project-URL: Homepage, https://github.com/tiagoBarbano/light-health
Project-URL: Repository, https://github.com/tiagoBarbano/light-health
Classifier: Programming Language :: Python :: 3
Classifier: Framework :: FastAPI
Classifier: Framework :: AsyncIO
Requires-Python: >=3.13
License-File: LICENSE
Requires-Dist: msgspec>=0.18
Dynamic: license-file
